orgdb/__init__.py
orgdb/_ahub.py
orgdb/orgdb.py
orgdb/orgdbregistry.py
orgdb/record.py
orgdb-0.0.1.dist-info/licenses/LICENSE.txt
orgdb-0.0.1.dist-info/METADATA
orgdb-0.0.1.dist-info/WHEEL
orgdb-0.0.1.dist-info/top_level.txt
orgdb-0.0.1.dist-info/RECORD
